heimdall/__init__.py
heimdall/gcs.py
heimdall/mail_mailjet.py
heimdall/pubsub.py
heimdall/secret_manager.py
heimdall_mail_notifier-0.1.dist-info/LICENCE
heimdall_mail_notifier-0.1.dist-info/METADATA
heimdall_mail_notifier-0.1.dist-info/WHEEL
heimdall_mail_notifier-0.1.dist-info/top_level.txt
heimdall_mail_notifier-0.1.dist-info/RECORD
