Metadata-Version: 2.1
Name: heimdall-mail-notifier
Version: 0.1
Summary: This module allow user to execute an SQL request in Bigquery and send the result in a mail attachment send by mailjet
Home-page: UNKNOWN
Author: Jean-Francois MARQUIS
Author-email: jeanfrancois.marquis@gmail.com
License: MIT
Platform: UNKNOWN
Requires-Dist: mailjet-rest (>=1.3.3)
Requires-Dist: google-cloud-secret-manager (>=0.2.0)
Requires-Dist: google-api-python-client (>=1.7.11)
Requires-Dist: google-auth (>=1.9.0)
Requires-Dist: google-cloud-bigquery (>=1.23.1)
Requires-Dist: google-cloud-core (>=1.1.0)
Requires-Dist: google-cloud-logging (>=1.14.0)
Requires-Dist: google-cloud-pubsub (>=1.1.0)
Requires-Dist: google-cloud-storage (>=1.23.0)
